simple_pastebin_parser/__init__.py
simple_pastebin_parser/paste.py
simple_pastebin_parser/utils.py
simple_pastebin_parser-0.5.2.dist-info/METADATA
simple_pastebin_parser-0.5.2.dist-info/WHEEL
simple_pastebin_parser-0.5.2.dist-info/top_level.txt
simple_pastebin_parser-0.5.2.dist-info/RECORD
