Metadata-Version: 2.1
Name: simple-pastebin-parser
Version: 0.5.2
Summary: a small web crawler for the pastebin.com website
Home-page: https://github.com/shlomikushchi/simple_pastebin_parser
Author: Shlomi Kushchi
Author-email: shlomik@example.com
License: UNKNOWN
Keywords: simple_pastebin_parser
Platform: UNKNOWN
Classifier: Development Status :: 2 - Pre-Alpha
Classifier: Intended Audience :: Developers
Classifier: Natural Language :: English
Classifier: Programming Language :: Python :: 3
Classifier: Programming Language :: Python :: 3.5
Classifier: Programming Language :: Python :: 3.6
Requires-Python: >=3.5
Requires-Dist: certifi (==2019.11.28)
Requires-Dist: chardet (==3.0.4)
Requires-Dist: idna (==2.9)
Requires-Dist: lxml (==4.5.0)
Requires-Dist: python-dateutil (==2.8.1)
Requires-Dist: requests (==2.23.0)
Requires-Dist: six (==1.14.0)
Requires-Dist: urllib3 (==1.25.8)
Requires-Dist: pytz (==2019.3)
Requires-Dist: pandas (==0.22.0)
Requires-Dist: numpy (==1.15.4)
